freeport/__init__.py
freeport/freeport.py
freeport/package_metadata.json
freeport-0.1.15.data/scripts/freeport
freeport-0.1.15.dist-info/AUTHORS.rst
freeport-0.1.15.dist-info/LICENSE
freeport-0.1.15.dist-info/METADATA
freeport-0.1.15.dist-info/WHEEL
freeport-0.1.15.dist-info/top_level.txt
freeport-0.1.15.dist-info/RECORD
