Metadata-Version: 1.1
Name: freeport
Version: 0.1.15
Summary: Simple Python library to free a port
Home-page: http://github.com/yashbathia/freeport
Author: Yash Bathia
Author-email: yash.bathia@yahoo.com
License: ISC
Platform: UNKNOWN
Classifier: License :: OSI Approved :: ISC License (ISCL)
Classifier: Operating System :: POSIX :: Linux
Classifier: Programming Language :: Python
